{
  "project_info": {
    "project_number": "639608576567",
    "firebase_url": "https://checkmypay-b0321.firebaseio.com",
    "project_id": "checkmypay-b0321",
    "storage_bucket": "checkmypay-b0321.appspot.com"
  },
  "client": [
    {
      "client_info": {
        "mobilesdk_app_id": "1:639608576567:android:bb0f621fe0b913b216bdb2",
        "android_client_info": {
          "package_name": "com.example.checkmypay"
        }
      },
      "oauth_client": [
        {
          "client_id": "639608576567-1o0sesmca91je5n9icqk7nv0toah71tn.apps.googleusercontent.com",
          "client_type": 1,
          "android_info": {
            "package_name": "com.example.checkmypay",
            "certificate_hash": "816aef7732c3462fc58c4d59875c5304d94fb89e"
          }
        },
        {
          "client_id": "639608576567-n9493eadb4q9edsaksb423u5p21jhj6k.apps.googleusercontent.com",
          "client_type": 3
        }
      ],
      "api_key": [
        {
          "current_key": "AIzaSyCnS1OkZZkVSYtfylsJF4P8UHTWxdFt8mQ"
        }
      ],
      "services": {
        "appinvite_service": {
          "other_platform_oauth_client": [
            {
              "client_id": "639608576567-n9493eadb4q9edsaksb423u5p21jhj6k.apps.googleusercontent.com",
              "client_type": 3
            }
          ]
        }
      }
    }
  ],
  "configuration_version": "1"
}